django_model_translator/__init__.py
django_model_translator/apps.py
django_model_translator/serializers.py
django_model_translator/tests.py
django_model_translator-0.1.dist-info/LICENSE
django_model_translator-0.1.dist-info/METADATA
django_model_translator-0.1.dist-info/WHEEL
django_model_translator-0.1.dist-info/top_level.txt
django_model_translator-0.1.dist-info/RECORD
