Metadata-Version: 2.1
Name: django-model-translator
Version: 0.1
Summary: Django Model Translator
Home-page: https://github.com/muhammadmamajonov/django-model-translator.git
Author: Muhammad Mamajonov
Author-email: muhammadbekmamajonov@gmail.com
License: MIT
Platform: UNKNOWN
Classifier: Environment :: Web Environment
Classifier: Framework :: Django
License-File: LICENSE
